LICENCE
flake8_import_rules.py
pyproject.toml
flake8_import_rules-1.0.0.dist-info/entry_points.txt
flake8_import_rules-1.0.0.dist-info/WHEEL
flake8_import_rules-1.0.0.dist-info/METADATA
flake8_import_rules-1.0.0.dist-info/RECORD
